aws_rfdk/__init__.py
aws_rfdk/py.typed
aws_rfdk/_jsii/__init__.py
aws_rfdk/_jsii/aws-rfdk@1.6.0.jsii.tgz
aws_rfdk/deadline/__init__.py
aws_rfdk-1.6.0.data/scripts/stage-deadline
aws_rfdk-1.6.0.dist-info/LICENSE
aws_rfdk-1.6.0.dist-info/METADATA
aws_rfdk-1.6.0.dist-info/NOTICE
aws_rfdk-1.6.0.dist-info/WHEEL
aws_rfdk-1.6.0.dist-info/top_level.txt
aws_rfdk-1.6.0.dist-info/RECORD
